mlflow_redisai/__init__.py
mlflow_redisai/cli.py
mlflow_redisai/utils.py
mlflow_redisai-0.1.0.dist-info/LICENSE
mlflow_redisai-0.1.0.dist-info/METADATA
mlflow_redisai-0.1.0.dist-info/WHEEL
mlflow_redisai-0.1.0.dist-info/entry_points.txt
mlflow_redisai-0.1.0.dist-info/top_level.txt
mlflow_redisai-0.1.0.dist-info/RECORD
