Metadata-Version: 2.1
Name: mlflow-redisai
Version: 0.1.0
Summary: MLFlow RedisAI integration package
Home-page: https://github.com/hhsecond/mlflow-redisai
Author: hhsecond
Author-email: sherin@tensorwerk.com
License: UNKNOWN
Platform: UNKNOWN
Classifier: Programming Language :: Python :: 3
Classifier: License :: OSI Approved :: Apache Software License
Classifier: Operating System :: OS Independent
Requires-Python: >=3.6
Requires-Dist: redisai
Requires-Dist: ml2rt
